cmaclp/SVM_prediction.py
cmaclp/__init__.py
cmaclp/tests/SVM_prediction_test.py
cmaclp/tests/__init__.py
cmaclp/tests/cmaclp_test_model.py
cmaclp-0.1.1.dist-info/LICENSE
cmaclp-0.1.1.dist-info/METADATA
cmaclp-0.1.1.dist-info/WHEEL
cmaclp-0.1.1.dist-info/entry_points.txt
cmaclp-0.1.1.dist-info/top_level.txt
cmaclp-0.1.1.dist-info/RECORD
