Metadata-Version: 2.1
Name: cmaclp
Version: 0.1.1
Summary: Corneal meta-atlas command line predictor
License-File: LICENSE
Requires-Dist: setuptools (<=57.5.0)
Requires-Dist: wheel
Requires-Dist: python-build
Requires-Dist: pytest-cov
Requires-Dist: h5py
Requires-Dist: numpy (<1.24,>=1.23.3)
Requires-Dist: pandas (>=1.4.4)
Requires-Dist: scikit-learn
Requires-Dist: scanpy (>=1.9.1)
Requires-Dist: importlib-resources
